expr_tracker/__init__.py
expr_tracker/_compat.py
expr_tracker/alert.py
expr_tracker/cli.py
expr_tracker/encoders.py
expr_tracker/jsonl.py
expr_tracker/tracker.py
expr_tracker/types.py
expr_tracker-0.1.6.dist-info/METADATA
expr_tracker-0.1.6.dist-info/WHEEL
expr_tracker-0.1.6.dist-info/entry_points.txt
expr_tracker-0.1.6.dist-info/RECORD
