Metadata-Version: 2.4
Name: expr_tracker
Version: 0.1.6
Summary: Add your description here
Author-email: HSPK <whxway@whu.edu.cn>
Requires-Python: >=3.10
Requires-Dist: jsonlines>=4.0.0
Requires-Dist: loguru>=0.7.3
Requires-Dist: slark>=0.1.28
Requires-Dist: wandb>=0.21.0
